odoo9_addon_account_tax_unece-9.0.1.0.0-py2.7-nspkg.pth
odoo_addons/account_tax_unece/__openerp__.py
odoo_addons/account_tax_unece/__init__.py
odoo_addons/account_tax_unece/README.rst
odoo_addons/account_tax_unece/models/account_tax.py
odoo_addons/account_tax_unece/models/unece_code_list.py
odoo_addons/account_tax_unece/models/__init__.py
odoo_addons/account_tax_unece/views/account_tax.xml
odoo_addons/account_tax_unece/data/unece_tax_categ.xml
odoo_addons/account_tax_unece/data/unece_tax_type.xml
odoo9_addon_account_tax_unece-9.0.1.0.0.dist-info/top_level.txt
odoo9_addon_account_tax_unece-9.0.1.0.0.dist-info/WHEEL
odoo9_addon_account_tax_unece-9.0.1.0.0.dist-info/RECORD
odoo9_addon_account_tax_unece-9.0.1.0.0.dist-info/metadata.json
odoo9_addon_account_tax_unece-9.0.1.0.0.dist-info/DESCRIPTION.rst
odoo9_addon_account_tax_unece-9.0.1.0.0.dist-info/METADATA
odoo9_addon_account_tax_unece-9.0.1.0.0.dist-info/namespace_packages.txt
